{
    "configurations": [
        {
            "name": "Linux",
            "includePath": [
                "${workspaceFolder}/**",
                ".",
                "..",
                "/usr/local/include/librealsense2/**",
                "/usr/local/include/**",
                "/usr/include/pcl-1.7",
                "/usr/include/eigen3"
            ],
            "defines": [],
            "compilerPath": "/usr/bin/gcc",
            "cStandard": "c11",
            "cppStandard": "c++11",
            "intelliSenseMode": "clang-x64"
        }
    ],
    "version": 4
}